ikcli/__init__.py
ikcli/cli.py
ikcli/algos/__init__.py
ikcli/algos/cli.py
ikcli/algos/core.py
ikcli/algos/local.py
ikcli/algos/templates/cookiecutter.json
ikcli/algos/templates/{{cookiecutter.plugin_dir}}/__init__.py
ikcli/algos/templates/{{cookiecutter.plugin_dir}}/readme.md
ikcli/algos/templates/{{cookiecutter.plugin_dir}}/requirements.txt
ikcli/algos/templates/{{cookiecutter.plugin_dir}}/{{cookiecutter.algo_name}}.py
ikcli/algos/templates/{{cookiecutter.plugin_dir}}/{{cookiecutter.algo_name}}_process.py
ikcli/algos/templates/{{cookiecutter.plugin_dir}}/{{cookiecutter.algo_name}}_test.py
ikcli/algos/templates/{{cookiecutter.plugin_dir}}/{{cookiecutter.algo_name}}_widget.py
ikcli/common/__init__.py
ikcli/common/cli.py
ikcli/common/core.py
ikcli/hub/__init__.py
ikcli/hub/cli.py
ikcli/hub/core.py
ikcli/namespaces/__init__.py
ikcli/namespaces/cli.py
ikcli/namespaces/core.py
ikcli/net/__init__.py
ikcli/net/api/__init__.py
ikcli/net/api/core.py
ikcli/net/api/exceptions.py
ikcli/net/api/pagination.py
ikcli/net/http/__init__.py
ikcli/net/http/auth.py
ikcli/net/http/core.py
ikcli/net/http/exceptions.py
ikcli/net/http/progress.py
ikcli/net/http/serializer.py
ikcli/organizations/__init__.py
ikcli/organizations/cli.py
ikcli/organizations/core.py
ikcli/projects/__init__.py
ikcli/projects/cli.py
ikcli/projects/core.py
ikcli/users/__init__.py
ikcli/users/core.py
ikcli/utils/__init__.py
ikcli/utils/path.py
ikcli/utils/rich.py
ikcli/utils/version.py
ikcli/workflows/__init__.py
ikcli/workflows/archive.py
ikcli/workflows/core.py
ikomia_cli-0.9.1.dist-info/METADATA
ikomia_cli-0.9.1.dist-info/WHEEL
ikomia_cli-0.9.1.dist-info/entry_points.txt
ikomia_cli-0.9.1.dist-info/top_level.txt
ikomia_cli-0.9.1.dist-info/RECORD
